topk_sdk-0.7.3.dist-info/METADATA
topk_sdk-0.7.3.dist-info/WHEEL
topk_sdk-0.7.3.dist-info/licenses/LICENSE
topk_sdk/__init__.py
topk_sdk/__init__.pyi
topk_sdk/data/__init__.py
topk_sdk/data/__init__.pyi
topk_sdk/error/__init__.py
topk_sdk/error/__init__.pyi
topk_sdk/py.typed
topk_sdk/query/__init__.py
topk_sdk/query/__init__.pyi
topk_sdk/schema/__init__.py
topk_sdk/schema/__init__.pyi
topk_sdk/topk_sdk.cpython-310-powerpc64le-linux-gnu.so
topk_sdk-0.7.3.dist-info/RECORD
