Metadata-Version: 2.4
Name: topk_sdk
Version: 0.7.3
Classifier: Programming Language :: Rust
Classifier: Programming Language :: Python :: Implementation :: CPython
Classifier: Programming Language :: Python :: Implementation :: PyPy
License-File: LICENSE
Summary: Python SDK for topk.io
Keywords: topk,search,vector,keyword,bm25
Home-Page: https://topk.io
Requires-Python: >=3.9
Project-URL: homepage, https://topk.io
Project-URL: documentation, https://docs.topk.io
Project-URL: repository, https://github.com/topk-io/topk
